LICENSE
MANIFEST.in
README.md
setup.cfg
setup.py
chat/__init__.py
chat/admin.py
chat/apps.py
chat/models.py
chat/tests.py
chat/views.py
chat/migrations/0001_initial.py
chat/migrations/__init__.py
config/__init__.py
config/asgi.py
config/settings.py
config/urls.py
config/wsgi.py
listing/__init__.py
listing/admin.py
listing/apps.py
listing/models.py
listing/tests.py
listing/views.py
listing/migrations/0001_initial.py
listing/migrations/__init__.py
location/__init__.py
location/admin.py
location/apps.py
location/models.py
location/tests.py
location/views.py
location/migrations/0001_initial.py
location/migrations/__init__.py
nomoney.shop.egg-info/PKG-INFO
nomoney.shop.egg-info/SOURCES.txt
nomoney.shop.egg-info/dependency_links.txt
nomoney.shop.egg-info/requires.txt
nomoney.shop.egg-info/top_level.txt
user/__init__.py
user/admin.py
user/apps.py
user/models.py
user/tests.py
user/views.py
user/migrations/0001_initial.py
user/migrations/__init__.py