Metadata-Version: 2.1
Name: nomoney.shop
Version: 0.1.0
Summary: Plattform to exchange goods and services and calculate possible deals direct and indirect
Home-page: https://github.com/snake-soft/nomoney.shop
Author: Snake-Soft
Author-email: info@snake-soft.com
License: UNKNOWN
Project-URL: Bug Reports, https://github.com/snake-soft/nomoney.shop/issues/
Project-URL: Source, https://github.com/snake-soft/nomoney.shop
Keywords: moneyless exchange platform
Platform: UNKNOWN
Classifier: Development Status :: 3 - Alpha
Classifier: Intended Audience :: Developers
Classifier: Topic :: System :: Filesystems
Classifier: License :: OSI Approved :: GNU General Public License v3 (GPLv3)
Classifier: Programming Language :: Python :: 3
Classifier: Programming Language :: Python :: 3.5
Classifier: Programming Language :: Python :: 3.6
Classifier: Programming Language :: Python :: 3.7
Classifier: Programming Language :: Python :: 3.8
Requires-Python: !=2.*, !=3.0.*, !=3.1.*, !=3.2.*, !=3.3.*, !=3.4.*, <4
Provides-Extra: test
Provides-Extra: dev
